sqlalchemy_create_object_operator/__init__.py
sqlalchemy_create_object_operator/sqlalchemy_create_object_operator.py
amsterdam_airflow_sqlalchemy_create_object_operator-1.3.dist-info/METADATA
amsterdam_airflow_sqlalchemy_create_object_operator-1.3.dist-info/WHEEL
amsterdam_airflow_sqlalchemy_create_object_operator-1.3.dist-info/RECORD
